<?xml version="1.0" encoding="UTF-8"?>
<mods xmlns:xlink="http://www.w3.org/1999/xlink"
      xmlns:xsi="http://www.w3.org/2001/XMLSchema-instance"
      xmlns="http://www.loc.gov/mods/v3"
      xsi:schemaLocation="http://www.loc.gov/mods/v3 http://www.loc.gov/standards/mods/v3/mods-3-5.xsd">
   <identifier type="local">omeka_007081</identifier>
   <identifier>CLIO id: 7745718</identifier>
   <titleInfo>
      <title>Ḥozeḳ yad ṿe-hu ha-yad ha-ḥazaḳah asher ʻasʹah Mosheh ben Maimon ṿe-ḥibarti..be-mahut ha-shir. 243 verso</title>
    </titleInfo>
   <titleInfo>
      <title>חוזק יד והוא היד החזקה אשר עשה משה בן מימון ...במהות השיר</title>
    </titleInfo>
   <physicalDescription>
      <digitalOrigin>reformatted digital</digitalOrigin>
      <form>manuscripts</form>
    </physicalDescription>
   <originInfo>
      <dateCreated encoding="w3cdtf" keyDate="yes">1636</dateCreated>
      <dateCreated>1636</dateCreated>
    </originInfo>
   <location>
      <physicalLocation authority="marcorg">NNC-RB</physicalLocation>
      <url access="object in context" usage="primary display">https://exhibitions.cul.columbia.edu/exhibits/show/hebrew_mss/humanities/x893_15_m88</url>
      <holdingSimple>
        <copyInformation>
            <shelfLocator>X893.15 M88</shelfLocator>
        </copyInformation>
      </holdingSimple>
    </location>
   <relatedItem displayLabel="Project" type="host">
      <titleInfo>
        <title>The People in the Books: Hebraica and Judaica Manuscripts from Columbia University Libraries</title>
      </titleInfo>
      <location>
        <url>http://www.columbia.edu/cgi-bin/cul/resolve?clio9680681</url>
      </location>
    </relatedItem>
   <relatedItem displayLabel="Collection" type="host">
      <titleInfo>
        <title>X Manuscripts</title>
      </titleInfo>
    </relatedItem>
   <note>original filename: 120017099.tif</note>
   <name>
      <namePart>Ibn Muvhar, Solomon ben Samuel</namePart>
    </name>
   <typeOfResource>still image</typeOfResource>
   <language>
      <languageTerm type="code" authority="iso639-2b">heb</languageTerm>
    </language>
   <recordInfo>
      <languageOfCataloging>
        <languageTerm type="code" authority="iso639-2b">eng</languageTerm>
      </languageOfCataloging>
      <recordContentSource authority="marcorg">NNC</recordContentSource>
      <recordOrigin>Created and edited in general conformance to MODS Guideline (Version 3).</recordOrigin>
    </recordInfo>
</mods>
